{"cameraMode":{"drawMode":0,"name":"Shaded","section":"Shading Mode"},"sceneLighting":true,"audioPlay":false,"sceneViewState":{"m_AlwaysRefresh":false,"showFog":true,"showSkybox":true,"showFlares":true,"showImageEffects":true,"showParticleSystems":true,"showVisualEffectGraphs":true,"m_FxEnabled":true},"in2DMode":false,"pivot":{"x":-11.968891143798829,"y":7.285237789154053,"z":16.86923599243164},"rotation":{"x":-0.03420734778046608,"y":-0.9633688926696777,"z":0.14884953200817109,"w":-0.2210204005241394},"size":11.164654731750489,"orthographic":false}